configs/AlphaDesign.py
configs/ESMIF.py
configs/GCA.py
configs/GVP.py
configs/GraphTrans.py
configs/KWDesign.py
configs/PiFold.py
configs/ProteinMPNN.py
configs/StructGNN.py
configs/__init__.py
evaluation_tools/Folding.py
evaluation_tools/InverseFolding.py
evaluation_tools/__init__.py
evaluation_tools/tools.py
src/__init__.py
src/version.py
src/datasets/__init__.py
src/datasets/alphafold_dataset.py
src/datasets/casp_dataset.py
src/datasets/cath_dataset.py
src/datasets/dataloader.py
src/datasets/deploy_utils.py
src/datasets/fast_dataloader.py
src/datasets/featurizer.py
src/datasets/mpnn_dataset.py
src/datasets/protein_rna_dataset.py
src/datasets/ts_dataset.py
src/datasets/utils.py
src/interface/__init__.py
src/interface/data_interface.py
src/interface/model_interface.py
src/interface/pretrain_interface.py
src/models/E3PiFold_model.py
src/models/MemoryESM.py
src/models/MemoryESMIF.py
src/models/MemoryPiFold.py
src/models/MemoryTuning.py
src/models/PretrainESMIF_model.py
src/models/PretrainESM_model.py
src/models/PretrainPiFold_model.py
src/models/Tuning.py
src/models/__init__.py
src/models/alphadesign_model.py
src/models/esmif_model.py
src/models/gca_model.py
src/models/graphtrans_model.py
src/models/gvp_model.py
src/models/kwdesign_model.py
src/models/pifold_model.py
src/models/proteinmpnn_model.py
src/models/structgnn_model.py
src/models/uniif_model.py
src/modules/E3PiFold.py
src/modules/__init__.py
src/modules/alphadesign_module.py
src/modules/esmif_module.py
src/modules/gca_module.py
src/modules/graphtrans_module.py
src/modules/gvp_module.py
src/modules/pifold_module.py
src/modules/pifold_module_old.py
src/modules/proteinmpnn_module.py
src/modules/uniif_module.py
src/tools/__init__.py
src/tools/affine_utils.py
src/tools/config_utils.py
src/tools/design_utils.py
src/tools/logger.py
src/tools/main_utils.py
src/tools/metrics.py
src/tools/parser.py
src/tools/utils.py
train/__init__.py
train/data_interface.py
train/deploy_utils.py
train/design_interface.py
ProteinInvBench-0.1.0.dist-info/METADATA
ProteinInvBench-0.1.0.dist-info/WHEEL
ProteinInvBench-0.1.0.dist-info/top_level.txt
ProteinInvBench-0.1.0.dist-info/RECORD
